hoocs/__init__.py
hoocs/approximate_shapley_values.py
hoocs/base_explainer.py
hoocs/derived_explainer_targeted.py
hoocs/helper_base.py
hoocs/helper_kernelshap.py
hoocs/helper_methods.py
hoocs/kernelshap.py
hoocs/preddiff.py
hoocs/shapley.py
hoocs/imputers/__init__.py
hoocs/imputers/abstract_imputer.py
hoocs/imputers/color_sampling_imputer.py
hoocs/imputers/opencv_inpainting.py
hoocs/imputers/simple_imputers.py
hoocs-0.0.1.dist-info/LICENSE
hoocs-0.0.1.dist-info/METADATA
hoocs-0.0.1.dist-info/WHEEL
hoocs-0.0.1.dist-info/top_level.txt
hoocs-0.0.1.dist-info/RECORD
