Metadata-Version: 2.1
Name: hoocs
Version: 0.0.1
Summary: Occlusion-based explainers for higher-order attributions.
Author-email: Stefan Bluecher <bluecher@tu-berlin.de>
License: GNU LESSER GENERAL PUBLIC LICENSE
Project-URL: Homepage, https://github.com/bluecher31/hoocs
Keywords: XAI,PredDiff,Shapley values,Interactions,Model-agnostic attributions
Classifier: Programming Language :: Python
Classifier: Programming Language :: Python :: 3
Requires-Python: >=3.8
License-File: LICENSE
Requires-Dist: numpy >1.20
Requires-Dist: scipy
Requires-Dist: matplotlib
Requires-Dist: opencv-python
Requires-Dist: scikit-learn
Provides-Extra: dev
Requires-Dist: pytest ; extra == 'dev'
